{
  "lastUpdated": "2026-07-09",
  "prices": {
    "PKO": {
      "close": 107.68,
      "change": 1.68,
      "changePercent": 1.58,
      "date": "2026-07-09",
      "volume": 2774827,
      "open": 106.42,
      "high": 108.56,
      "low": 106.42
    },
    "PKN": {
      "close": 139.44,
      "change": -0.52,
      "changePercent": -0.37,
      "date": "2026-07-09",
      "volume": 1465419,
      "open": 139,
      "high": 139.86,
      "low": 137.94
    },
    "KGH": {
      "close": 304.6,
      "change": 6.9,
      "changePercent": 2.32,
      "date": "2026-07-09",
      "volume": 741094,
      "open": 304.95,
      "high": 307.25,
      "low": 301.45
    },
    "PZU": {
      "close": 67.56,
      "change": -0.14,
      "changePercent": -0.21,
      "date": "2026-07-09",
      "volume": 1538941,
      "open": 68,
      "high": 68.66,
      "low": 67.28
    },
    "PEO": {
      "close": 235.4,
      "change": 0.4,
      "changePercent": 0.17,
      "date": "2026-07-09",
      "volume": 881853,
      "open": 235,
      "high": 239.4,
      "low": 235
    },
    "CDR": {
      "close": 231.5,
      "change": -3,
      "changePercent": -1.28,
      "date": "2026-07-09",
      "volume": 201453,
      "open": 236,
      "high": 236.6,
      "low": 230.6
    },
    "MOD": {
      "close": 99,
      "change": 0,
      "changePercent": 0,
      "date": "2026-07-09",
      "volume": 260899,
      "open": 99.96,
      "high": 100.25,
      "low": 98
    },
    "DNP": {
      "close": 27.75,
      "change": -0.05,
      "changePercent": -0.18,
      "date": "2026-07-09",
      "volume": 2131696,
      "open": 27.94,
      "high": 28.41,
      "low": 27.7
    },
    "LPP": {
      "close": 18800,
      "change": 130,
      "changePercent": 0.7,
      "date": "2026-07-09",
      "volume": 2529,
      "open": 18680,
      "high": 18870,
      "low": 18580
    },
    "CPS": {
      "close": 15.4,
      "change": -0.04,
      "changePercent": -0.26,
      "date": "2026-07-09",
      "volume": 444936,
      "open": 15.57,
      "high": 15.61,
      "low": 15.27
    },
    "MBK": {
      "close": 1395,
      "change": -9,
      "changePercent": -0.64,
      "date": "2026-07-09",
      "volume": 19230,
      "open": 1406,
      "high": 1438,
      "low": 1386
    },
    "JSW": {
      "close": 25.01,
      "change": -0.12,
      "changePercent": -0.48,
      "date": "2026-07-09",
      "volume": 151606,
      "open": 25.25,
      "high": 25.6,
      "low": 24.91
    },
    "PGE": {
      "close": 9.31,
      "change": -0.05,
      "changePercent": -0.53,
      "date": "2026-07-09",
      "volume": 2287537,
      "open": 9.39,
      "high": 9.52,
      "low": 9.22
    },
    "KRU": {
      "close": 409.1,
      "change": -8.5,
      "changePercent": -2.04,
      "date": "2026-07-09",
      "volume": 42321,
      "open": 418.3,
      "high": 424.5,
      "low": 402.2
    },
    "PCO": {
      "close": 38.2,
      "change": 1.7,
      "changePercent": 4.66,
      "date": "2026-07-09",
      "volume": 2356093,
      "open": 37.5,
      "high": 38.55,
      "low": 36.75
    },
    "ACP": {
      "close": 176.45,
      "change": -0.75,
      "changePercent": -0.42,
      "date": "2026-07-09",
      "volume": 92413,
      "open": 178.05,
      "high": 180,
      "low": 174.25
    },
    "OPL": {
      "close": 13.78,
      "change": -0.16,
      "changePercent": -1.15,
      "date": "2026-07-09",
      "volume": 1111952,
      "open": 13.94,
      "high": 14.02,
      "low": 13.77
    },
    "ALR": {
      "close": 138.75,
      "change": 2.75,
      "changePercent": 2.02,
      "date": "2026-07-09",
      "volume": 217912,
      "open": 136,
      "high": 139.3,
      "low": 135.5
    },
    "KTY": {
      "close": 1208,
      "change": 19,
      "changePercent": 1.6,
      "date": "2026-07-09",
      "volume": 17718,
      "open": 1199,
      "high": 1216,
      "low": 1190
    }
  }
}